cansig/__init__.py
cansig/_version.py
cansig/filesys.py
cansig/gsea.py
cansig/logger.py
cansig/multirun.py
cansig/tutorial.py
cansig/types.py
cansig/_preprocessing/__init__.py
cansig/_preprocessing/_infercnv.py
cansig/_preprocessing/annotation.py
cansig/_preprocessing/data.py
cansig/_preprocessing/infercnv.py
cansig/_preprocessing/main.py
cansig/_preprocessing/plotting.py
cansig/_preprocessing/quality_control.py
cansig/_preprocessing/scoring.py
cansig/_preprocessing/subclonal.py
cansig/_preprocessing/utils.py
cansig/cluster/__init__.py
cansig/cluster/api.py
cansig/cluster/leiden.py
cansig/cnvanalysis/__init__.py
cansig/cnvanalysis/differentialcnvs.py
cansig/integration/_CONSTANTS.py
cansig/integration/__init__.py
cansig/integration/model.py
cansig/integration/utils.py
cansig/integration/base/__init__.py
cansig/integration/base/model.py
cansig/integration/base/module.py
cansig/integration/data/__init__.py
cansig/integration/data/datasplitter.py
cansig/integration/data/fields.py
cansig/integration/module/__init__.py
cansig/integration/module/batcheffectvae.py
cansig/integration/module/cnvvae.py
cansig/integration/module/vae.py
cansig/integration/training/__init__.py
cansig/integration/training/runner.py
cansig/integration/training/trainer.py
cansig/integration/training/training_plan.py
cansig/interface/__init__.py
cansig/interface/cluster.py
cansig/metaanalysis/__init__.py
cansig/metaanalysis/heatmap.py
cansig/metaanalysis/repr_directory.py
cansig/metasignatures/WRC.py
cansig/metasignatures/__init__.py
cansig/metasignatures/api.py
cansig/metasignatures/clustering.py
cansig/metasignatures/utils.py
cansig/models/__init__.py
cansig/models/api.py
cansig/models/cansig.py
cansig/models/scvi.py
cansig/plotting/__init__.py
cansig/plotting/plotting.py
cansig/run/__init__.py
cansig/run/download.py
cansig/run/format.py
cansig/run/heatmap.py
cansig/run/integration.py
cansig/run/metasignatures.py
cansig/run/pipeline.py
cansig/run/postprocessing.py
cansig/run/split.py
cansig-0.3.1.dist-info/LICENSE
cansig-0.3.1.dist-info/METADATA
cansig-0.3.1.dist-info/WHEEL
cansig-0.3.1.dist-info/top_level.txt
cansig-0.3.1.dist-info/RECORD
