Metadata-Version: 2.1
Name: cansig
Version: 0.3.1
Summary: Discovering de novo shared transcriptional programs in single cancer cells
Home-page: https://github.com/BoevaLab/CanSig
Platform: any
License-File: LICENSE
Requires-Dist: anndata
Requires-Dist: gseapy
Requires-Dist: infercnvpy
Requires-Dist: leidenalg
Requires-Dist: matplotlib
Requires-Dist: numpy (<=1.21)
Requires-Dist: pandas
Requires-Dist: petname
Requires-Dist: pydantic
Requires-Dist: scanpy (>=1.9.1)
Requires-Dist: seaborn
Requires-Dist: scipy
Requires-Dist: scvi-tools (>=0.20.0)
Requires-Dist: statsmodels
Requires-Dist: protobuf (~=3.19.0)
Provides-Extra: test
Requires-Dist: pytest ; extra == 'test'
Requires-Dist: pytest-cov ; extra == 'test'
Requires-Dist: scikit-learn ; extra == 'test'
